{
  "generatedBy": "scripts/update_status.py",
  "lastRunLocal": "2025-12-27T01:21:18-06:00",
  "lastRunUtc": "2025-12-27T07:21:18+00:00",
  "localTimezone": "America/Chicago",
  "note": "Automated site metadata update (scheduled).",
  "run": {
    "actor": "taminulislam",
    "ref": "refs/heads/main",
    "repository": "taminulislam/taminulislam.github.io",
    "runAttempt": "1",
    "runId": "20536029398",
    "sha": "483ef838d413abe12e6e4f9f2d9ba68814e0d321",
    "workflow": "Scheduled status update"
  }
}
